.pre-commit-config.yaml
CHANGES.rst
CONTRIBUTORS.rst
DEVELOP.rst
LICENSE.GPL
LICENSE.rst
MANIFEST.in
Makefile
README.rst
requirements.txt
setup.cfg
setup.py
tox.ini
docs/conf.py
docs/index.rst
src/collective/__init__.py
src/collective.behavior.lastmodifier.egg-info/PKG-INFO
src/collective.behavior.lastmodifier.egg-info/SOURCES.txt
src/collective.behavior.lastmodifier.egg-info/dependency_links.txt
src/collective.behavior.lastmodifier.egg-info/entry_points.txt
src/collective.behavior.lastmodifier.egg-info/namespace_packages.txt
src/collective.behavior.lastmodifier.egg-info/not-zip-safe
src/collective.behavior.lastmodifier.egg-info/requires.txt
src/collective.behavior.lastmodifier.egg-info/top_level.txt
src/collective/behavior/__init__.py
src/collective/behavior/lastmodifier/__init__.py
src/collective/behavior/lastmodifier/behavior.py
src/collective/behavior/lastmodifier/configure.zcml
src/collective/behavior/lastmodifier/testing.py
src/collective/behavior/lastmodifier/locales/README.rst
src/collective/behavior/lastmodifier/locales/__init__.py
src/collective/behavior/lastmodifier/locales/collective.behavior.lastmodifier.pot
src/collective/behavior/lastmodifier/locales/update.py
src/collective/behavior/lastmodifier/locales/update.sh
src/collective/behavior/lastmodifier/locales/en/LC_MESSAGES/collective.behavior.lastmodifier.po
src/collective/behavior/lastmodifier/tests/__init__.py
src/collective/behavior/lastmodifier/tests/test_behavior.py