Metadata-Version: 2.1
Name: collective.behavior.lastmodifier
Version: 1.0.0rc2
Summary: Adds a behavior that tracks down the last user that modified an object
Home-page: https://github.com/collective/collective.behavior.lastmodifier
Author: ale-rt
Author-email: pisa@syslab.com
License: GPL version 2
Keywords: Python Plone
Platform: UNKNOWN
Classifier: Development Status :: 5 - Production/Stable
Classifier: Environment :: Web Environment
Classifier: Framework :: Plone
Classifier: Framework :: Plone :: Addon
Classifier: Framework :: Plone :: 5.2
Classifier: Programming Language :: Python
Classifier: Programming Language :: Python :: 3 :: Only
Classifier: Programming Language :: Python :: 3.6
Classifier: Programming Language :: Python :: 3.7
Classifier: Programming Language :: Python :: 3.8
Classifier: Operating System :: OS Independent
Classifier: License :: OSI Approved :: GNU General Public License v2 (GPLv2)
Requires-Python: >=3.6
Provides-Extra: test
